pulumi_sdwan/__init__.py
pulumi_sdwan/_inputs.py
pulumi_sdwan/_utilities.py
pulumi_sdwan/activate_centralized_policy.py
pulumi_sdwan/advanced_inspection_profile_policy_definition.py
pulumi_sdwan/advanced_malware_protection_policy_definition.py
pulumi_sdwan/allow_url_list_policy_object.py
pulumi_sdwan/app_probe_class_policy_object.py
pulumi_sdwan/application_aware_routing_policy_definition.py
pulumi_sdwan/application_list_policy_object.py
pulumi_sdwan/application_priority_feature_profile.py
pulumi_sdwan/application_priority_qos_policy.py
pulumi_sdwan/application_priority_traffic_policy_policy.py
pulumi_sdwan/as_path_list_policy_object.py
pulumi_sdwan/attach_feature_device_template.py
pulumi_sdwan/block_url_list_policy_object.py
pulumi_sdwan/cedge_aaa_feature_template.py
pulumi_sdwan/cedge_global_feature_template.py
pulumi_sdwan/cedge_igmp_feature_template.py
pulumi_sdwan/cedge_multicast_feature_template.py
pulumi_sdwan/cedge_pim_feature_template.py
pulumi_sdwan/cellular_cedge_profile_feature_template.py
pulumi_sdwan/cellular_controller_feature_template.py
pulumi_sdwan/cellular_profile_feature_template.py
pulumi_sdwan/centralized_policy.py
pulumi_sdwan/cflowd_policy_definition.py
pulumi_sdwan/cisco_banner_feature_template.py
pulumi_sdwan/cisco_bfd_feature_template.py
pulumi_sdwan/cisco_bgp_feature_template.py
pulumi_sdwan/cisco_dhcp_server_feature_template.py
pulumi_sdwan/cisco_logging_feature_template.py
pulumi_sdwan/cisco_ntp_feature_template.py
pulumi_sdwan/cisco_omp_feature_template.py
pulumi_sdwan/cisco_ospf_feature_template.py
pulumi_sdwan/cisco_ospfv3_feature_template.py
pulumi_sdwan/cisco_secure_internet_gateway_feature_template.py
pulumi_sdwan/cisco_security_feature_template.py
pulumi_sdwan/cisco_sig_credentials_feature_template.py
pulumi_sdwan/cisco_snmp_feature_template.py
pulumi_sdwan/cisco_system_feature_template.py
pulumi_sdwan/cisco_thousandeyes_feature_template.py
pulumi_sdwan/cisco_trustsec_feature_template.py
pulumi_sdwan-0.5.2.dist-info/METADATA
pulumi_sdwan-0.5.2.dist-info/WHEEL
pulumi_sdwan-0.5.2.dist-info/top_level.txt
pulumi_sdwan-0.5.2.dist-info/RECORD
